grafx/__init__.py
grafx/utils.py
grafx/data/__init__.py
grafx/data/batch.py
grafx/data/configs.py
grafx/data/conversion.py
grafx/data/graph.py
grafx/data/tensor.py
grafx/draw/__init__.py
grafx/draw/bezier.py
grafx/draw/edge.py
grafx/draw/graph.py
grafx/draw/node.py
grafx/draw/position.py
grafx/draw/style.py
grafx/processors/__init__.py
grafx/processors/container.py
grafx/processors/delay.py
grafx/processors/dynamics.py
grafx/processors/eq.py
grafx/processors/filter.py
grafx/processors/nonlinear.py
grafx/processors/reverb.py
grafx/processors/stereo.py
grafx/processors/core/__init__.py
grafx/processors/core/convolution.py
grafx/processors/core/delay.py
grafx/processors/core/envelope.py
grafx/processors/core/fft_filterbank.py
grafx/processors/core/fir.py
grafx/processors/core/geq.py
grafx/processors/core/iir.py
grafx/processors/core/midside.py
grafx/processors/core/noise.py
grafx/processors/core/scale.py
grafx/processors/core/utils.py
grafx/render/__init__.py
grafx/render/core.py
grafx/render/graph.py
grafx/render/prepare.py
grafx/render/order/__init__.py
grafx/render/order/graph.py
grafx/render/order/tensor.py
GRAFX-0.6.0.dist-info/LICENSE
GRAFX-0.6.0.dist-info/METADATA
GRAFX-0.6.0.dist-info/WHEEL
GRAFX-0.6.0.dist-info/top_level.txt
GRAFX-0.6.0.dist-info/RECORD
