Metadata-Version: 2.1
Name: GRAFX
Version: 0.6.0
Summary: An Open-Source Library For Audio Processing Graphs in PyTorch
Author: Sungho Lee
Author-email: sh-lee@snu.ac.kr
Requires-Python: >=3.10
License-File: LICENSE
Requires-Dist: torch
Requires-Dist: torch-geometric
Requires-Dist: numpy
Requires-Dist: matplotlib
Requires-Dist: networkx
Requires-Dist: einops
Requires-Dist: torchlpc>=0.4
Requires-Dist: torchcomp
